treelite_runtime-3.9.1.dist-info/RECORD
treelite_runtime-3.9.1.dist-info/WHEEL
treelite_runtime-3.9.1.dist-info/top_level.txt
treelite_runtime-3.9.1.dist-info/METADATA
treelite_runtime/predictor.py
treelite_runtime/util.py
treelite_runtime/__init__.py
treelite_runtime/warn.py
treelite_runtime/VERSION
treelite_runtime/libpath.py
treelite_runtime/.dylibs/libomp.dylib
treelite_runtime/lib/libtreelite_runtime.dylib
